kaggle_discussion_extractor/__init__.py
kaggle_discussion_extractor/cli.py
kaggle_discussion_extractor/core.py
kaggle_discussion_extractor/leaderboard.py
kaggle_discussion_extractor/notebook_downloader.py
kaggle_discussion_extractor/writeup_extractor.py
kaggle_discussion_extractor-1.2.0.dist-info/METADATA
kaggle_discussion_extractor-1.2.0.dist-info/WHEEL
kaggle_discussion_extractor-1.2.0.dist-info/entry_points.txt
kaggle_discussion_extractor-1.2.0.dist-info/top_level.txt
kaggle_discussion_extractor-1.2.0.dist-info/RECORD
