Metadata-Version: 2.4
Name: kaggle-discussion-extractor
Version: 1.2.0
Summary: A professional-grade tool for extracting and analyzing discussions from Kaggle competitions
Home-page: https://github.com/Letemoin/kaggle-discussion-extractor
Author: Kaggle Discussion Extractor Contributors
Author-email: contact@kaggle-extractor.com
Maintainer: Kaggle Discussion Extractor Contributors
License: MIT
Project-URL: Homepage, https://github.com/Letemoin/kaggle-discussion-extractor
Project-URL: Documentation, https://github.com/Letemoin/kaggle-discussion-extractor#readme
Project-URL: Repository, https://github.com/Letemoin/kaggle-discussion-extractor
Project-URL: Bug Tracker, https://github.com/Letemoin/kaggle-discussion-extractor/issues
Keywords: kaggle,discussion,extractor,web-scraping,data-extraction,machine-learning,competition,playwright,async
Classifier: Development Status :: 5 - Production/Stable
Classifier: Intended Audience :: Developers
Classifier: Intended Audience :: Science/Research
Classifier: License :: OSI Approved :: MIT License
Classifier: Operating System :: OS Independent
Classifier: Programming Language :: Python :: 3
Classifier: Programming Language :: Python :: 3.8
Classifier: Programming Language :: Python :: 3.9
Classifier: Programming Language :: Python :: 3.10
Classifier: Programming Language :: Python :: 3.11
Classifier: Programming Language :: Python :: 3.12
Classifier: Topic :: Software Development :: Libraries :: Python Modules
Classifier: Topic :: Internet :: WWW/HTTP :: Dynamic Content
Classifier: Topic :: Scientific/Engineering :: Information Analysis
Requires-Python: >=3.8
Requires-Dist: playwright>=1.40.0
Requires-Dist: nbformat>=5.0.0
Requires-Dist: nbconvert>=6.0.0
Provides-Extra: dev
Requires-Dist: pytest>=7.4.3; extra == "dev"
Requires-Dist: pytest-asyncio>=0.21.1; extra == "dev"
Requires-Dist: black>=23.11.0; extra == "dev"
Requires-Dist: flake8>=6.1.0; extra == "dev"
Requires-Dist: mypy>=1.7.0; extra == "dev"
Requires-Dist: coverage>=7.3.2; extra == "dev"
Requires-Dist: pre-commit>=3.5.0; extra == "dev"
Provides-Extra: enhanced
Requires-Dist: beautifulsoup4>=4.12.2; extra == "enhanced"
Requires-Dist: lxml>=4.9.3; extra == "enhanced"
Requires-Dist: tqdm>=4.66.1; extra == "enhanced"
Dynamic: author-email
Dynamic: home-page
Dynamic: requires-python
